digikala_api/__init__.py
digikala_api/base.py
digikala_api/error.py
digikala_api/request.py
digikala_api-0.1.1.dist-info/LICENSE
digikala_api-0.1.1.dist-info/METADATA
digikala_api-0.1.1.dist-info/WHEEL
digikala_api-0.1.1.dist-info/top_level.txt
digikala_api-0.1.1.dist-info/RECORD
