Metadata-Version: 2.1
Name: digikala_api
Version: 0.1.1
Summary: With this package you can easily access the Digikala API to get information about products details.
Author-email: Moein Arabi <moein.mo81@gmail.com>
License: MIT License
Project-URL: Homepage, https://github.com/ILoveBacteria/digikala-api
Project-URL: Issues, https://github.com/ILoveBacteria/digikala-api/issues
Classifier: Programming Language :: Python :: 3
Classifier: License :: OSI Approved :: MIT License
Classifier: Operating System :: OS Independent
Requires-Python: >=3.10
License-File: LICENSE
Requires-Dist: requests==2.32.3
